[{"user":{"$oid":"6415826cfc13ae691b000104"},"title":"4-600 - Corrosion-Resistant Masonry","description":"Appl ext fix-radius/ulna","assignedTo":"frontOfHouse","priority":"Jr","status":"Open"},
{"user":{"$oid":"6415826cfc13ae691b000105"},"title":"17-040 - Profit","description":"Endosc destruc esoph les","assignedTo":"frontOfHouse","priority":"II","status":"completed"},
{"user":{"$oid":"6415826cfc13ae691b000106"},"title":"1-000 - Purpose","description":"Remov other GI device","assignedTo":"frontOfHouse","priority":"IV","status":"Open"},
{"user":{"$oid":"6415826cfc13ae691b000107"},"title":"15-700 - Heating, Venting and Air Conditioning","description":"Lac canaliculi incision","assignedTo":"backOfHouse","priority":"Sr","status":"Open"},
{"user":{"$oid":"6415826cfc13ae691b000108"},"title":"9-300 - Tile","description":"Fit arm prosthesis NOS","assignedTo":"frontOfHouse","priority":"Sr","status":"Open"},
{"user":{"$oid":"6415826cfc13ae691b000109"},"title":"14-700 - Turntables","description":"Hemodialysis","assignedTo":"frontOfHouse","priority":"Sr","status":"completed"},
{"user":{"$oid":"6415826cfc13ae691b00010a"},"title":"16-500 - Lighting","description":"Lid reconst w hair graft","assignedTo":"backOfHouse","priority":"Sr","status":"completed"},
{"user":{"$oid":"6415826cfc13ae691b00010b"},"title":"7-800 - Fire and Smoke Protection","description":"Disarticulation of ankle","assignedTo":"backOfHouse","priority":"Sr","status":"completed"},
{"user":{"$oid":"6415826cfc13ae691b00010c"},"title":"2-900 - Landscaping","description":"Rep anuls fibros NEC/NOS","assignedTo":"backOfHouse","priority":"II","status":"Open"},
{"user":{"$oid":"6415826cfc13ae691b00010d"},"title":"4-700 - Simulated Masonry","description":"Cell blk/pap NEC","assignedTo":"frontOfHouse","priority":"III","status":"Open"},
{"user":{"$oid":"6415826cfc13ae691b00010e"},"title":"11-120 - Vending Equipment","description":"Anal biopsy","assignedTo":"backOfHouse","priority":"III","status":"Open"},
{"user":{"$oid":"6415826cfc13ae691b00010f"},"title":"1-640 - Owner Furnished Products","description":"Arthrocentesis","assignedTo":"backOfHouse","priority":"III","status":"Open"},
{"user":{"$oid":"6415826cfc13ae691b000110"},"title":"1-014 - Project Executive","description":"Metacarpocarpal fusion","assignedTo":"backOfHouse","priority":"Sr","status":"inProgress"},
{"user":{"$oid":"6415826cfc13ae691b000111"},"title":"17 - Markup and Contingency","description":"Replace prolapsed cord","assignedTo":"backOfHouse","priority":"III","status":"Open"},
{"user":{"$oid":"6415826cfc13ae691b000112"},"title":"17-010 - Contingency","description":"Suture of gum laceration","assignedTo":"backOfHouse","priority":"IV","status":"Open"},
{"user":{"$oid":"6415826cfc13ae691b000113"},"title":"2-200 - Site Preparation","description":"Percu nephrostmy w frag","assignedTo":"backOfHouse","priority":"II","status":"inProgress"},
{"user":{"$oid":"6415826cfc13ae691b000114"},"title":"11-900 - Exhibit Equipment","description":"Extracorporeal memb oxy","assignedTo":"backOfHouse","priority":"Jr","status":"completed"},
{"user":{"$oid":"6415826cfc13ae691b000115"},"title":"15-200 - Process Piping","description":"Remove corneal implant","assignedTo":"backOfHouse","priority":"Jr","status":"inProgress"},
{"user":{"$oid":"6415826cfc13ae691b000116"},"title":"1-600 - Product Requirements (Scope of Work)","description":"Cystogram NEC","assignedTo":"frontOfHouse","priority":"Sr","status":"completed"},
{"user":{"$oid":"6415826cfc13ae691b000117"},"title":"1-570 - Temporary Controls","description":"Sympath nerve inject NEC","assignedTo":"frontOfHouse","priority":"III","status":"Open"},
{"user":{"$oid":"6415826cfc13ae691b000118"},"title":"4-600 - Corrosion-Resistant Masonry","description":"Lap abltn liver les/tiss","assignedTo":"backOfHouse","priority":"II","status":"inProgress"},
{"user":{"$oid":"6415826cfc13ae691b000119"},"title":"13-175 - Ice Rinks","description":"Urethrostomy closure","assignedTo":"frontOfHouse","priority":"II","status":"completed"},
{"user":{"$oid":"6415826cfc13ae691b00011a"},"title":"2-795 - Porous Paving","description":"Drug addict counselling","assignedTo":"backOfHouse","priority":"II","status":"inProgress"},
{"user":{"$oid":"6415826cfc13ae691b00011b"},"title":"14-900 - Transportation","description":"Knee synovectomy","assignedTo":"frontOfHouse","priority":"IV","status":"Open"},
{"user":{"$oid":"6415826cfc13ae691b00011c"},"title":"5-700 - Ornamental Metal","description":"Stereo radiosurgery NEC","assignedTo":"backOfHouse","priority":"Jr","status":"completed"},
{"user":{"$oid":"6415826cfc13ae691b00011d"},"title":"1-640 - Owner Furnished Products","description":"Electrocardiograph monit","assignedTo":"frontOfHouse","priority":"Sr","status":"Open"},
{"user":{"$oid":"6415826cfc13ae691b00011e"},"title":"3-500 - Cementitious Decks and Underlayments","description":"Excise tib/fib for graft","assignedTo":"backOfHouse","priority":"Jr","status":"Open"},
{"user":{"$oid":"6415826cfc13ae691b00011f"},"title":"2-936 - Fertilizer","description":"Excis les lacrimal gland","assignedTo":"backOfHouse","priority":"IV","status":"completed"},
{"user":{"$oid":"6415826cfc13ae691b000120"},"title":"5-600 - Hydraulic Fabrications","description":"Repair of hammer toe","assignedTo":"backOfHouse","priority":"Sr","status":"inProgress"},
{"user":{"$oid":"6415826cfc13ae691b000121"},"title":"12-500 - Furniture","description":"Insert skel musc stimula","assignedTo":"backOfHouse","priority":"IV","status":"inProgress"},
{"user":{"$oid":"6415826cfc13ae691b000122"},"title":"9-700 - Wall Finishes","description":"Perc ather extracran vsl","assignedTo":"backOfHouse","priority":"IV","status":"Open"},
{"user":{"$oid":"6415826cfc13ae691b000123"},"title":"4-200 - Masonry Units","description":"Intravascul imaging NEC","assignedTo":"frontOfHouse","priority":"II","status":"Open"},
{"user":{"$oid":"6415826cfc13ae691b000124"},"title":"2-621 - Foundatation Drainage Piping","description":"Other heart valve ops","assignedTo":"backOfHouse","priority":"III","status":"inProgress"},
{"user":{"$oid":"6415826cfc13ae691b000125"},"title":"16-700 - Communications","description":"Root canal w apicoectomy","assignedTo":"backOfHouse","priority":"Sr","status":"completed"},
{"user":{"$oid":"6415826cfc13ae691b000126"},"title":"9-100 - Metal Support Assemblies","description":"Unilat lung transplant","assignedTo":"backOfHouse","priority":"II","status":"inProgress"},
{"user":{"$oid":"6415826cfc13ae691b000127"},"title":"2-924 - Sodding","description":"Remve ext hrt assist sys","assignedTo":"backOfHouse","priority":"IV","status":"Open"},
{"user":{"$oid":"6415826cfc13ae691b000128"},"title":"8-100 - Doors","description":"Remove FB lens NOS","assignedTo":"backOfHouse","priority":"II","status":"Open"},
{"user":{"$oid":"6415826cfc13ae691b000129"},"title":"1-530 - Temporary Construction","description":"Scrotum & tunica i & d","assignedTo":"backOfHouse","priority":"Jr","status":"Open"},
{"user":{"$oid":"6415826cfc13ae691b00012a"},"title":"2-740 - Flexible Pavement Asphalt Pavement","description":"Opn abltn liver les/tiss","assignedTo":"frontOfHouse","priority":"III","status":"Open"},
{"user":{"$oid":"6415826cfc13ae691b00012b"},"title":"9-680 - Carpet","description":"Percut tunica aspiration","assignedTo":"backOfHouse","priority":"IV","status":"completed"},
{"user":{"$oid":"6415826cfc13ae691b00012c"},"title":"5-100 - Structural Metals","description":"Facial bone dx proc NEC","assignedTo":"backOfHouse","priority":"IV","status":"Open"},
{"user":{"$oid":"6415826cfc13ae691b00012d"},"title":"4-900 - Masonry Restoration and Cleaning","description":"Gum operation NEC","assignedTo":"frontOfHouse","priority":"II","status":"Open"},
{"user":{"$oid":"6415826cfc13ae691b00012e"},"title":"15-200 - Process Piping","description":"Part breech extract NEC","assignedTo":"backOfHouse","priority":"III","status":"completed"},
{"user":{"$oid":"6415826cfc13ae691b00012f"},"title":"10-700 - Exterior Protection","description":"Refus lmb/lmbsc ant/post","assignedTo":"frontOfHouse","priority":"II","status":"completed"},
{"user":{"$oid":"6415826cfc13ae691b000130"},"title":"11-200 - Water Supply and Treatment Equipment","description":"Replace wound catheter","assignedTo":"frontOfHouse","priority":"II","status":"inProgress"},
{"user":{"$oid":"6415826cfc13ae691b000131"},"title":"2-783 - Interlocking Concrete Unit Paving","description":"Tooth restor by filling","assignedTo":"backOfHouse","priority":"III","status":"Open"},
{"user":{"$oid":"6415826cfc13ae691b000132"},"title":"14-900 - Transportation","description":"Mesenteric repair NEC","assignedTo":"backOfHouse","priority":"IV","status":"inProgress"},
{"user":{"$oid":"6415826cfc13ae691b000133"},"title":"10-900 - Wardrobe and Closet Specialties","description":"Release of chordee","assignedTo":"backOfHouse","priority":"II","status":"inProgress"},
{"user":{"$oid":"6415826cfc13ae691b000134"},"title":"2-220 - Site Demolition","description":"Syn implant to face bone","assignedTo":"backOfHouse","priority":"Jr","status":"inProgress"},
{"user":{"$oid":"6415826cfc13ae691b000135"},"title":"8-700 - Hardware","description":"Dental restoration NEC","assignedTo":"backOfHouse","priority":"II","status":"Open"},
{"user":{"$oid":"6415826cfc13ae691b000136"},"title":"7-600 - Flashing and Sheet Metal","description":"Hindquarter amputation","assignedTo":"frontOfHouse","priority":"Sr","status":"completed"},
{"user":{"$oid":"6415826cfc13ae691b000137"},"title":"3-600 - Grouts","description":"Lap bi dr/ind ing hrn-gr","assignedTo":"frontOfHouse","priority":"Jr","status":"inProgress"},
{"user":{"$oid":"6415826cfc13ae691b000138"},"title":"2-230 - Site Clearing","description":"Lap scervic hysterectomy","assignedTo":"frontOfHouse","priority":"Jr","status":"Open"},
{"user":{"$oid":"6415826cfc13ae691b000139"},"title":"6 - Wood and Plastics","description":"Remove tracheostomy tube","assignedTo":"backOfHouse","priority":"IV","status":"completed"},
{"user":{"$oid":"6415826cfc13ae691b00013a"},"title":"3-210 - Cast-In-Place Concrete","description":"Metatars/tars inj op NOS","assignedTo":"backOfHouse","priority":"Jr","status":"inProgress"},
{"user":{"$oid":"6415826cfc13ae691b00013b"},"title":"11-130 - Audio-Visual Equipment","description":"Decompression chamber","assignedTo":"frontOfHouse","priority":"Jr","status":"completed"},
{"user":{"$oid":"6415826cfc13ae691b00013c"},"title":"13-100 - Lightning Protection","description":"Lap marsup ovarian cyst","assignedTo":"frontOfHouse","priority":"Jr","status":"Open"},
{"user":{"$oid":"6415826cfc13ae691b00013d"},"title":"5 - Metals","description":"Percutaneous pyelogram","assignedTo":"frontOfHouse","priority":"IV","status":"completed"},
{"user":{"$oid":"6415826cfc13ae691b00013e"},"title":"11-600 - Laboratory Equipment","description":"Remove ocular implant","assignedTo":"backOfHouse","priority":"III","status":"Open"},
{"user":{"$oid":"6415826cfc13ae691b00013f"},"title":"13-240 - Oxygenation Systems","description":"Failed forceps","assignedTo":"backOfHouse","priority":"III","status":"inProgress"},
{"user":{"$oid":"6415826cfc13ae691b000140"},"title":"2-781 - Asphalt Pavers","description":"Closed pancreatic biopsy","assignedTo":"backOfHouse","priority":"Jr","status":"completed"},
{"user":{"$oid":"6415826cfc13ae691b000141"},"title":"11-040 - Ecclesiastical Equipment","description":"Psychia interv/eval NEC","assignedTo":"backOfHouse","priority":"II","status":"completed"},
{"user":{"$oid":"6415826cfc13ae691b000142"},"title":"11-020 - Security and Vault Equipment","description":"Heart septa repair NOS","assignedTo":"frontOfHouse","priority":"Sr","status":"inProgress"},
{"user":{"$oid":"6415826cfc13ae691b000143"},"title":"11-660 - Observatory Equipment","description":"Replace nephrostomy tube","assignedTo":"frontOfHouse","priority":"III","status":"inProgress"},
{"user":{"$oid":"6415826cfc13ae691b000144"},"title":"13-030 - Special Purpose Rooms","description":"Pros repair atria def-cl","assignedTo":"backOfHouse","priority":"Sr","status":"Open"},
{"user":{"$oid":"6415826cfc13ae691b000145"},"title":"1-712 - Local Conditions","description":"Other bronchial excision","assignedTo":"frontOfHouse","priority":"IV","status":"inProgress"},
{"user":{"$oid":"6415826cfc13ae691b000146"},"title":"1-630 - Product Substitution Procedures","description":"Oth unilat oophorectomy","assignedTo":"frontOfHouse","priority":"IV","status":"Open"},
{"user":{"$oid":"6415826cfc13ae691b000147"},"title":"11-900 - Exhibit Equipment","description":"Imp crtd sinus stm,totl","assignedTo":"backOfHouse","priority":"Jr","status":"completed"},
{"user":{"$oid":"6415826cfc13ae691b000148"},"title":"12-800 - Interior Plants and Planters","description":"Amputation thru humerus","assignedTo":"backOfHouse","priority":"Jr","status":"Open"},
{"user":{"$oid":"6415826cfc13ae691b000149"},"title":"9-900 - Paints and Coatings","description":"Resect ext seg sm bowel","assignedTo":"frontOfHouse","priority":"Sr","status":"completed"},
{"user":{"$oid":"6415826cfc13ae691b00014a"},"title":"1-630 - Product Substitution Procedures","description":"Vulvar diagnos proc NEC","assignedTo":"frontOfHouse","priority":"III","status":"inProgress"},
{"user":{"$oid":"6415826cfc13ae691b00014b"},"title":"7 - Thermal and Moisture Protection","description":"Ext auditory canal incis","assignedTo":"backOfHouse","priority":"II","status":"inProgress"},
{"user":{"$oid":"6415826cfc13ae691b00014c"},"title":"15-950 - Testing, Adjusting, and Balancing","description":"Unilateral adrenalectomy","assignedTo":"frontOfHouse","priority":"Sr","status":"Open"},
{"user":{"$oid":"6415826cfc13ae691b00014d"},"title":"13-550 - Transportation Control Instrumentation","description":"Fit up arm/should prosth","assignedTo":"backOfHouse","priority":"III","status":"Open"},
{"user":{"$oid":"6415826cfc13ae691b00014e"},"title":"1-740 - Cleaning","description":"Blepharorrhaphy severing","assignedTo":"frontOfHouse","priority":"Sr","status":"completed"},
{"user":{"$oid":"6415826cfc13ae691b00014f"},"title":"2-784 - Stone Unit Pavers","description":"Otoscopy","assignedTo":"frontOfHouse","priority":"III","status":"completed"},
{"user":{"$oid":"6415826cfc13ae691b000150"},"title":"10-530 - Protective Covers","description":"Ventri shunt-uninary sys","assignedTo":"frontOfHouse","priority":"II","status":"Open"},
{"user":{"$oid":"6415826cfc13ae691b000151"},"title":"2-782 - Brick Pavers","description":"Incision of heart NOS","assignedTo":"frontOfHouse","priority":"Jr","status":"completed"},
{"user":{"$oid":"6415826cfc13ae691b000152"},"title":"13-200 - Storage Tanks","description":"Urethral sphincter emg","assignedTo":"frontOfHouse","priority":"Sr","status":"inProgress"},
{"user":{"$oid":"6415826cfc13ae691b000153"},"title":"2-260 - Excavation Support and Protection","description":"Endocervical biopsy","assignedTo":"frontOfHouse","priority":"IV","status":"inProgress"},
{"user":{"$oid":"6415826cfc13ae691b000154"},"title":"5-500 - Metal Fabrications","description":"Peripheral nerve graft","assignedTo":"backOfHouse","priority":"IV","status":"completed"},
{"user":{"$oid":"6415826cfc13ae691b000155"},"title":"11-150 - Parking Control Equipment","description":"Occlude leg vein NEC","assignedTo":"backOfHouse","priority":"Sr","status":"inProgress"},
{"user":{"$oid":"6415826cfc13ae691b000156"},"title":"4-800 - Masonry Assemblies","description":"Ins part disc pros cerv","assignedTo":"frontOfHouse","priority":"Jr","status":"completed"},
{"user":{"$oid":"6415826cfc13ae691b000157"},"title":"5-100 - Structural Metals","description":"Open valvuloplasty NOS","assignedTo":"frontOfHouse","priority":"Sr","status":"Open"},
{"user":{"$oid":"6415826cfc13ae691b000158"},"title":"17-030 - Bond","description":"Stretching of fascia","assignedTo":"backOfHouse","priority":"IV","status":"inProgress"},
{"user":{"$oid":"6415826cfc13ae691b000159"},"title":"11-070 - Instrumental Equipment","description":"Int or repl lead epicar","assignedTo":"frontOfHouse","priority":"IV","status":"inProgress"},
{"user":{"$oid":"6415826cfc13ae691b00015a"},"title":"11-010 - Maintenance Equipment","description":"Auto hem stem ct w purg","assignedTo":"backOfHouse","priority":"III","status":"Open"},
{"user":{"$oid":"6415826cfc13ae691b00015b"},"title":"10-800 - Toilet, Bath, and Laundry Specialties","description":"Aortcor bypas-4+ cor art","assignedTo":"backOfHouse","priority":"Jr","status":"inProgress"},
{"user":{"$oid":"6415826cfc13ae691b00015c"},"title":"7-800 - Fire and Smoke Protection","description":"Inject bursa of hand","assignedTo":"frontOfHouse","priority":"IV","status":"Open"},
{"user":{"$oid":"6415826cfc13ae691b00015d"},"title":"4-400 - Stone","description":"Stern sm bowel interpos","assignedTo":"backOfHouse","priority":"IV","status":"completed"},
{"user":{"$oid":"6415826cfc13ae691b00015e"},"title":"1-013 - Project Coordinator","description":"Clos endoscopic lung bx","assignedTo":"backOfHouse","priority":"Jr","status":"Open"},
{"user":{"$oid":"6415826cfc13ae691b00015f"},"title":"3-600 - Grouts","description":"Bronchial repair NEC","assignedTo":"frontOfHouse","priority":"III","status":"inProgress"},
{"user":{"$oid":"6415826cfc13ae691b000160"},"title":"10-270 - Access Flooring","description":"Fus/refus 2-3 vertebrae","assignedTo":"frontOfHouse","priority":"II","status":"inProgress"},
{"user":{"$oid":"6415826cfc13ae691b000161"},"title":"12-500 - Furniture","description":"Imp/rep subcue card dev","assignedTo":"backOfHouse","priority":"III","status":"inProgress"},
{"user":{"$oid":"6415826cfc13ae691b000162"},"title":"8-300 - Specialty Doors","description":"Scleral operation NEC","assignedTo":"frontOfHouse","priority":"Jr","status":"completed"},
{"user":{"$oid":"6415826cfc13ae691b000163"},"title":"7-700 - Roof Specialties and Accessories","description":"Endo insrt bronc def/sub","assignedTo":"backOfHouse","priority":"IV","status":"completed"},
{"user":{"$oid":"6415826cfc13ae691b000164"},"title":"2-800 - Site Amenities","description":"Nephrotomogram NEC","assignedTo":"frontOfHouse","priority":"Sr","status":"completed"},
{"user":{"$oid":"6415826cfc13ae691b000165"},"title":"9-100 - Metal Support Assemblies","description":"Skull flap formation","assignedTo":"backOfHouse","priority":"II","status":"Open"},
{"user":{"$oid":"6415826cfc13ae691b000166"},"title":"5-600 - Hydraulic Fabrications","description":"Temp-inf intrcap lens ex","assignedTo":"frontOfHouse","priority":"IV","status":"completed"},
{"user":{"$oid":"6415826cfc13ae691b000167"},"title":"2-822 - Ornamental Metal Fences and Gates","description":"Applic ext fix dev NEC","assignedTo":"frontOfHouse","priority":"III","status":"inProgress"}]